pydispatch_sphinx/__init__.py
pydispatch_sphinx/directives.py
pydispatch_sphinx/documenters.py
python_dispatch_sphinx-0.2.2.dist-info/LICENSE
python_dispatch_sphinx-0.2.2.dist-info/METADATA
python_dispatch_sphinx-0.2.2.dist-info/WHEEL
python_dispatch_sphinx-0.2.2.dist-info/top_level.txt
python_dispatch_sphinx-0.2.2.dist-info/RECORD
