Metadata-Version: 2.1
Name: python-dispatch-sphinx
Version: 0.2.2
Summary: Sphinx extension for python-dispatch
Home-page: https://github.com/nocarryr/python-dispatch
Author: Matthew Reid
Author-email: matt@nomadic-recording.com
License: MIT
Project-URL: Documentation, https://python-dispatch.readthedocs.io
Project-URL: Source, https://github.com/nocarryr/python-dispatch
Project-URL: Tracker, https://github.com/nocarryr/python-dispatch/issues
Platform: any
Classifier: Development Status :: 2 - Pre-Alpha
Classifier: Natural Language :: English
Classifier: Operating System :: OS Independent
Classifier: Programming Language :: Python :: 3
Classifier: Programming Language :: Python :: 3.6
Classifier: Programming Language :: Python :: 3.7
Classifier: Programming Language :: Python :: 3.8
Classifier: Programming Language :: Python :: 3.9
Classifier: Programming Language :: Python :: 3.10
Classifier: Programming Language :: Python :: 3.11
Classifier: Intended Audience :: Developers
Classifier: Framework :: Sphinx
Classifier: Framework :: Sphinx :: Extension
Classifier: Topic :: Documentation
Classifier: Topic :: Documentation :: Sphinx
Classifier: Topic :: Software Development :: Libraries
Classifier: Topic :: Software Development :: Libraries :: Python Modules
Classifier: Topic :: Software Development :: Documentation
License-File: LICENSE
Requires-Dist: python-dispatch
Requires-Dist: sphinx (<5,>=4.5)
Requires-Dist: importlib-metadata ; python_version < "3.8"
